spetro/__init__.py
spetro/calibration/__init__.py
spetro/calibration/calibrator.py
spetro/calibration/optimizers.py
spetro/core/__init__.py
spetro/core/backends.py
spetro/core/engine.py
spetro/core/models.py
spetro/core/schemes.py
spetro/neural/__init__.py
spetro/neural/networks.py
spetro/neural/surrogate.py
spetro/pricing/__init__.py
spetro/pricing/monte_carlo.py
spetro/pricing/payoffs.py
spetro/pricing/pricer.py
spetro-0.1.3.dist-info/licenses/LICENSE
spetro-0.1.3.dist-info/METADATA
spetro-0.1.3.dist-info/WHEEL
spetro-0.1.3.dist-info/top_level.txt
spetro-0.1.3.dist-info/RECORD
